----------------------------------------------------------------
params annotations

----------------------------------------------------------------
rc
0
----------------------------------------------------------------
public class com.example.Generated_0
  minor version: 0
  major version: 55
  flags: (0x0021) ACC_PUBLIC, ACC_SUPER
  this_class: #2                          // com/example/Generated_0
  super_class: #4                         // java/lang/Object
  interfaces: 0, fields: 0, methods: 1, attributes: 0
Constant pool:
   #1 = Utf8               com/example/Generated_0
   #2 = Class              #1             // com/example/Generated_0
   #3 = Utf8               java/lang/Object
   #4 = Class              #3             // java/lang/Object
   #5 = Utf8               <init>
   #6 = Utf8               ()V
   #7 = NameAndType        #5:#6          // "<init>":()V
   #8 = Methodref          #4.#7          // java/lang/Object."<init>":()V
   #9 = Utf8               Code
{
  public com.example.Generated_0();
    descriptor: ()V
    flags: (0x0001) ACC_PUBLIC
    Code:
      stack=2, locals=1, args_size=1
         0: aload_0
         1: dup
         2: invokespecial #8                  // Method java/lang/Object."<init>":()V
         5: pop
         6: return
}

----------------------------------------------------------------

----------------------------------------------------------------
