----------------------------------------------------------------
params annotations
- Jsr380DynamicClassTest.ParameterConfig(type=class java.time.chrono.HijrahDate, annotations=[interface jakarta.validation.constraints.Past, interface jakarta.validation.constraints.PastOrPresent])
- Jsr380DynamicClassTest.ParameterConfig(type=class java.time.Year, annotations=[interface jakarta.validation.constraints.PastOrPresent, interface jakarta.validation.constraints.Null])
- Jsr380DynamicClassTest.ParameterConfig(type=interface java.util.Map, annotations=[interface jakarta.validation.constraints.NotEmpty])
- Jsr380DynamicClassTest.ParameterConfig(type=boolean, annotations=[interface jakarta.validation.constraints.AssertFalse])
- Jsr380DynamicClassTest.ParameterConfig(type=class [Ljava.lang.Object;, annotations=[])
----------------------------------------------------------------
.bytecode 55.0
.class public synchronized com/example/Generated_804815953
.super java/lang/Object
.implements org/jmolecules/ddd/types/ValueObject

.method public <init>(Ljava/time/chrono/HijrahDate;Ljava/time/Year;Ljava/util/Map;Z[Ljava/lang/Object;)V
.annotation visible Ljakarta/validation/constraints/Past;
groups ; empty array annotation value
message s = "{jakarta.validation.constraints.Past.message}"
payload ; empty array annotation value
.end annotation
.annotation visible Ljakarta/validation/constraints/PastOrPresent;
groups ; empty array annotation value
message s = "{jakarta.validation.constraints.PastOrPresent.message}"
payload ; empty array annotation value
.end annotation
.annotation visible Ljakarta/validation/constraints/PastOrPresent;
groups ; empty array annotation value
message s = "{jakarta.validation.constraints.PastOrPresent.message}"
payload ; empty array annotation value
.end annotation
.annotation visible Ljakarta/validation/constraints/Null;
groups ; empty array annotation value
message s = "{jakarta.validation.constraints.Null.message}"
payload ; empty array annotation value
.end annotation
.annotation visible Ljakarta/validation/constraints/NotEmpty;
groups ; empty array annotation value
message s = "{jakarta.validation.constraints.NotEmpty.message}"
payload ; empty array annotation value
.end annotation
.annotation visible Ljakarta/validation/constraints/AssertFalse;
groups ; empty array annotation value
message s = "{jakarta.validation.constraints.AssertFalse.message}"
payload ; empty array annotation value
.end annotation
aload 1
aload 2
aload 3
iload 4
aload 5
invokestatic com/example/Generated_804815953/validate(Ljava/time/chrono/HijrahDate;Ljava/time/Year;Ljava/util/Map;Z[Ljava/lang/Object;)V
aload 0
aload 1
aload 2
aload 3
iload 4
aload 5
aconst_null
invokespecial com/example/Generated_804815953/<init>(Ljava/time/chrono/HijrahDate;Ljava/time/Year;Ljava/util/Map;Z[Ljava/lang/Object;Lcom/example/Generated_804815953$auxiliary$[AUXILIARY_1];)V
return
.limit locals 6
.limit stack 7
.end method
.dep com/example/Generated_804815953;validate
.dep com/example/Generated_804815953;<init>
.provide com/example/Generated_804815953;<init>
.desc (Ljava/time/chrono/HijrahDate;Ljava/time/Year;Ljava/util/Map;Z[Ljava/lang/Object;)V
.desc (Ljava/time/chrono/HijrahDate;Ljava/time/Year;Ljava/util/Map;Z[Ljava/lang/Object;Lcom/example/Generated_804815953$auxiliary$[AUXILIARY_1];)V

.method private synthetic <init>(Ljava/time/chrono/HijrahDate;Ljava/time/Year;Ljava/util/Map;Z[Ljava/lang/Object;Lcom/example/Generated_804815953$auxiliary$[AUXILIARY_1];)V
aload 0
dup
invokespecial java/lang/Object/<init>()V
pop
return
.limit locals 7
.limit stack 2
.end method
.dep java/lang/Object;<init>
.provide com/example/Generated_804815953;<init>
.desc ()V

.method private static validate(Ljava/time/chrono/HijrahDate;Ljava/time/Year;Ljava/util/Map;Z[Ljava/lang/Object;)V
aload 0
ifnull L0
aload 0
invokestatic java/time/chrono/HijrahDate/now()Ljava/time/chrono/HijrahDate;
invokevirtual java/time/chrono/HijrahDate/isBefore(Ljava/time/chrono/ChronoLocalDate;)Z
ifne L0
new java/lang/IllegalArgumentException
dup
ldc "arg0 must be a past date"
invokespecial java/lang/IllegalArgumentException/<init>(Ljava/lang/String;)V
athrow
L0:
.stack
locals Object java/time/chrono/HijrahDate
locals Object java/time/Year
locals Object java/util/Map
locals Integer
locals Object [Ljava/lang/Object;
.end stack
aload 0
ifnull L1
aload 0
invokestatic java/time/chrono/HijrahDate/now()Ljava/time/chrono/HijrahDate;
invokevirtual java/time/chrono/HijrahDate/isAfter(Ljava/time/chrono/ChronoLocalDate;)Z
ifeq L1
new java/lang/IllegalArgumentException
dup
ldc "arg0 must be a date in the past or in the present"
invokespecial java/lang/IllegalArgumentException/<init>(Ljava/lang/String;)V
athrow
L1:
.stack
locals Object java/time/chrono/HijrahDate
locals Object java/time/Year
locals Object java/util/Map
locals Integer
locals Object [Ljava/lang/Object;
.end stack
aload 1
ifnull L2
aload 1
invokestatic java/time/Year/now()Ljava/time/Year;
invokevirtual java/time/Year/isAfter(Ljava/time/Year;)Z
ifeq L2
new java/lang/IllegalArgumentException
dup
ldc "arg1 must be a date in the past or in the present"
invokespecial java/lang/IllegalArgumentException/<init>(Ljava/lang/String;)V
athrow
L2:
.stack
locals Object java/time/chrono/HijrahDate
locals Object java/time/Year
locals Object java/util/Map
locals Integer
locals Object [Ljava/lang/Object;
.end stack
aload 1
ifnull L3
new java/lang/IllegalArgumentException
dup
ldc "arg1 must be null"
invokespecial java/lang/IllegalArgumentException/<init>(Ljava/lang/String;)V
athrow
L3:
.stack
locals Object java/time/chrono/HijrahDate
locals Object java/time/Year
locals Object java/util/Map
locals Integer
locals Object [Ljava/lang/Object;
.end stack
aload 2
ifnonnull L4
new java/lang/NullPointerException
dup
ldc "arg2 must not be empty"
invokespecial java/lang/NullPointerException/<init>(Ljava/lang/String;)V
athrow
L4:
.stack
locals Object java/time/chrono/HijrahDate
locals Object java/time/Year
locals Object java/util/Map
locals Integer
locals Object [Ljava/lang/Object;
.end stack
aload 2
invokeinterface java/util/Map/size()I 0
ifgt L5
new java/lang/IllegalArgumentException
dup
ldc "arg2 must not be empty"
invokespecial java/lang/IllegalArgumentException/<init>(Ljava/lang/String;)V
athrow
L5:
.stack
locals Object java/time/chrono/HijrahDate
locals Object java/time/Year
locals Object java/util/Map
locals Integer
locals Object [Ljava/lang/Object;
.end stack
iload 3
ifeq L6
new java/lang/IllegalArgumentException
dup
ldc "arg3 must be false"
invokespecial java/lang/IllegalArgumentException/<init>(Ljava/lang/String;)V
athrow
L6:
.stack
locals Object java/time/chrono/HijrahDate
locals Object java/time/Year
locals Object java/util/Map
locals Integer
locals Object [Ljava/lang/Object;
.end stack
return
.limit locals 5
.limit stack 3
.end method
.dep java/util/Map;size
.dep java/time/Year;isAfter
.dep java/lang/NullPointerException;<init>
.dep java/time/chrono/HijrahDate;isAfter
.dep java/time/Year;now
.dep java/time/chrono/HijrahDate;now
.dep java/time/chrono/HijrahDate;isBefore
.dep java/lang/IllegalArgumentException;<init>
.provide com/example/Generated_804815953;validate
.desc ()I
.desc ()Ljava/time/Year;
.desc ()Ljava/time/chrono/HijrahDate;
.desc (Ljava/lang/String;)V
.desc (Ljava/time/Year;)Z
.desc (Ljava/time/chrono/ChronoLocalDate;)Z

----------------------------------------------------------------
